    {
  "surah001": "የመክፈቻ ምዕራፍ",
  "surah002": "የላም ምዕራፍ",
  "surah003": "የዒምራን ቤተሰብ ምዕራፍ",
  "surah004": "የሴቶች ምዕራፍ",
  "surah005": "የማዕድ ምዕራፍ",
  "surah006": "የቤት እንስሳት ምዕራፍ",
  "surah007": "የአዕራፍ ምዕራፍ",
  "surah008": "የጦር ምርኮ ምዕራፍ",
  "surah009": "የንስሐ ምዕራፍ",
  "surah010": "የዩኑስ ምዕራፍ",
  "surah011": "የሁድ ምዕራፍ",
  "surah012": "የዩሱፍ ምዕራፍ",
  "surah013": "የነጎድጓድ ምዕራፍ",
  "surah014": "የኢብራሂም ምዕራፍ",
  "surah015": "የድንጋይ ሸለቆ ምዕራፍ",
  "surah016": "የንብ ምዕራፍ",
  "surah017": "የሌሊት ጉዞ ምዕራፍ",
  "surah018": "የዋሻ ምዕራፍ",
  "surah019": "የመርየም ምዕራፍ",
  "surah020": "የጣሀ ምዕራፍ",
  "surah021": "የነቢያት ምዕራፍ",
  "surah022": "የሐጅ ምዕራፍ",
  "surah023": "የምእመናን ምዕራፍ",
  "surah024": "የብርሃን ምዕራፍ",
  "surah025": "የመለኪያ ምዕራፍ",
  "surah026": "የባለቅኔዎች ምዕራፍ",
  "surah027": "የጉንዳን ምዕራፍ",
  "surah028": "የታሪኮች ምዕራፍ",
  "surah029": "የሸረሪት ምዕራፍ",
  "surah030": "የሮም ምዕራፍ",
  "surah031": "የሉቅማን ምዕራፍ",
  "surah032": "የስግደት ምዕራፍ",
  "surah033": "የቡድኖች ምዕራፍ",
  "surah034": "የሰባዕ ምዕራፍ",
  "surah035": "የፈጣሪ ምዕራፍ",
  "surah036": "የያሲን ምዕራፍ",
  "surah037": "የተሰላፊዎች ምዕራፍ",
  "surah038": "የሷድ ምዕራፍ",
  "surah039": "የጭፍሮች ምዕራፍ",
  "surah040": "የመሀሪ ምዕራፍ",
  "surah041": "የተብራሩ ምዕራፍ",
  "surah042": "የምክክር ምዕራፍ",
  "surah043": "የጌጣጌጥ ምዕራፍ",
  "surah044": "የጭስ ምዕራፍ",
  "surah045": "የተንበርካኪ ምዕራፍ",
  "surah046": "የአሸዋ ክምር ምዕራፍ",
  "surah047": "የሙሐመድ ምዕራፍ",
  "surah048": "የድል ምዕራፍ",
  "surah049": "የክፍሎች ምዕራፍ",
  "surah050": "የቃፍ ምዕራፍ",
  "surah051": "የበታኞች ምዕራፍ",
  "surah052": "የተራራ ምዕራፍ",
  "surah053": "የኮከብ ምዕራፍ",
  "surah054": "የጨረቃ ምዕራፍ",
  "surah055": "የአል-ረሕማን ምዕራፍ",
  "surah056": "የክስተት ምዕራፍ",
  "surah057": "የብረት ምዕራፍ",
  "surah058": "የተከራካሪዋ ምዕራፍ",
  "surah059": "የማባረር ምዕራፍ",
  "surah060": "የተፈታኟ ምዕራፍ",
  "surah061": "የሰልፍ ምዕራፍ",
  "surah062": "የአርብ ምዕራፍ",
  "surah063": "የመናፍቃን ምዕራፍ",
  "surah064": "የመሸናነፍ ምዕራፍ",
  "surah065": "የፍቺ ምዕራፍ",
  "surah066": "የማዕቀብ ምዕራፍ",
  "surah067": "የንግስና ምዕራፍ",
  "surah068": "የብዕር ምዕራፍ",
  "surah069": "የእርግጥኛዋ ምዕራፍ",
  "surah070": "የመሰላል ምዕራፍ",
  "surah071": "የኑሕ ምዕራፍ",
  "surah072": "የጂን ምዕራፍ",
  "surah073": "የተከናነበው ምዕራፍ",
  "surah074": "የተሸፈነው ምዕራፍ",
  "surah075": "የትንሳኤ ምዕራፍ",
  "surah076": "የሰው ምዕራፍ",
  "surah077": "የተላኪዎች ምዕራፍ",
  "surah078": "የታላቅ ዜና ምዕራፍ",
  "surah079": "የነጣቂዎች ምዕራፍ",
  "surah080": "ፊቱን አጨፈገገ ምዕራፍ",
  "surah081": "የመጠቅለል ምዕራፍ",
  "surah082": "የመከፈት ምዕራፍ",
  "surah083": "የአጭበርባሪዎች ምዕራፍ",
  "surah084": "የመሰንጠቅ ምዕራፍ",
  "surah085": "የህብረ ከዋክብት ምዕራፍ",
  "surah086": "የሌሊት መጪው ምዕራፍ",
  "surah087": "የልዑል ምዕራፍ",
  "surah088": "የሸፋኟ ምዕራፍ",
  "surah089": "የጎህ ምዕራፍ",
  "surah090": "የሀገር ምዕራፍ",
  "surah091": "የፀሐይ ምዕራፍ",
  "surah092": "የሌሊት ምዕራፍ",
  "surah093": "የረፋድ ምዕራፍ",
  "surah094": "የማስፋት ምዕራፍ",
  "surah095": "የበለስ ምዕራፍ",
  "surah096": "የረጋ ደም ምዕራፍ",
  "surah097": "የውሳኔ ምዕራፍ",
  "surah098": "የግልጽ ማስረጃ ምዕራፍ",
  "surah099": "የመንቀጥቀጥ ምዕራፍ",
  "surah100": "የሯጮች ምዕራፍ",
  "surah101": "የአስደንጋጭቱ ምዕራፍ",
  "surah102": "የመፎካከር ምዕራፍ",
  "surah103": "የጊዜ ምዕራፍ",
  "surah104": "የሐሜተኛ ምዕራፍ",
  "surah105": "የዝሆን ምዕራፍ",
  "surah106": "የቁረይሽ ምዕራፍ",
  "surah107": "የዕርዳታ ምዕራፍ",
  "surah108": "የከውሠር ምዕራፍ",
  "surah109": "የከሀዲዎች ምዕራፍ",
  "surah110": "የአላህ እርዳታ ምዕራፍ",
  "surah111": "የዘንባባ ገመድ ምዕራፍ",
  "surah112": "የጥራት ምዕራፍ",
  "surah113": "የጎህ መቅደድ ምዕራፍ",
  "surah114": "የሰዎች ምዕራፍ"
}